segmentation-0.2.2.dist-info/WHEEL
segmentation-0.2.2.dist-info/top_level.txt
segmentation-0.2.2.dist-info/entry_points.txt
segmentation-0.2.2.dist-info/RECORD
segmentation-0.2.2.dist-info/METADATA
segmentation-0.2.2.dist-info/LICENSE
segmentation/version.py
segmentation/segmentation.cpython-38-x86_64-linux-gnu.so
segmentation/__init__.py
segmentation/cli.py
segmentation/watershed.py
