Metadata-Version: 2.1
Name: segmentation
Version: 0.2.2
Summary: Mixture model segmentation
Home-page: https://github.com/usajusaj/segmentation
Author: Matej Usaj
Author-email: m.usaj@utoronto.ca
License: UNKNOWN
Download-URL: https://github.com/usajusaj/segmentation/archive/master.zip
Keywords: mixture,model,segmentation
Platform: UNKNOWN
Classifier: Development Status :: 5 - Production/Stable
Classifier: Intended Audience :: Science/Research
Classifier: Topic :: Scientific/Engineering :: Bio-Informatics
Classifier: License :: OSI Approved :: MIT License
Classifier: Programming Language :: Python :: 2
Classifier: Programming Language :: Python :: 2.7
Classifier: Programming Language :: Python :: 3
Classifier: Programming Language :: Python :: 3.5
Classifier: Programming Language :: Python :: 3.6
Classifier: Programming Language :: Python :: 3.7
Classifier: Programming Language :: Python :: 3.8
Requires-Dist: numpy
Requires-Dist: scipy
Requires-Dist: scikit-image
